minimal_docx/__init__.py
minimal_docx-0.1.dist-info/licenses/LICENSE
minimal_docx-0.1.dist-info/WHEEL
minimal_docx-0.1.dist-info/METADATA
minimal_docx-0.1.dist-info/RECORD
