Metadata-Version: 2.4
Name: minimal_docx
Version: 0.1
Summary: Minimalist manipulation of docx files
Author: eszense
License-Expression: GPL-3.0-or-later
License-File: LICENSE
